d2_png.py
d2_png-0.4.dist-info/METADATA
d2_png-0.4.dist-info/WHEEL
d2_png-0.4.dist-info/entry_points.txt
d2_png-0.4.dist-info/top_level.txt
d2_png-0.4.dist-info/RECORD
