Metadata-Version: 2.1
Name: d2-png
Version: 0.4
Summary: simple crontab implemented on thread executor pool
Home-page: https://github.com/weaming/d2-png
Author: weaming
Author-email: garden.yuen@gmail.com
License: UNKNOWN
Project-URL: Source, https://github.com/weaming/d2-png
Project-URL: Bug Reports, https://github.com/weaming/d2-png
Keywords: tools,markdown
Platform: UNKNOWN
Requires-Dist: imgkit
Requires-Dist: requests
Requires-Dist: printable
